odoo/addons/stock_package_type_category/README.rst
odoo/addons/stock_package_type_category/__init__.py
odoo/addons/stock_package_type_category/__manifest__.py
odoo/addons/stock_package_type_category/demo/stock_package_type_category.xml
odoo/addons/stock_package_type_category/i18n/it.po
odoo/addons/stock_package_type_category/i18n/stock_package_type_category.pot
odoo/addons/stock_package_type_category/models/__init__.py
odoo/addons/stock_package_type_category/models/stock_package_type.py
odoo/addons/stock_package_type_category/models/stock_package_type_category.py
odoo/addons/stock_package_type_category/readme/CONFIGURE.md
odoo/addons/stock_package_type_category/readme/CONTEXT.md
odoo/addons/stock_package_type_category/readme/CONTRIBUTORS.md
odoo/addons/stock_package_type_category/readme/DESCRIPTION.md
odoo/addons/stock_package_type_category/security/stock_package_type_category.xml
odoo/addons/stock_package_type_category/static/description/icon.png
odoo/addons/stock_package_type_category/static/description/index.html
odoo/addons/stock_package_type_category/tests/__init__.py
odoo/addons/stock_package_type_category/tests/test_stock_package_type_category.py
odoo/addons/stock_package_type_category/views/stock_package_type.xml
odoo/addons/stock_package_type_category/views/stock_package_type_category.xml
odoo_addon_stock_package_type_category-16.0.1.0.0.7.dist-info/METADATA
odoo_addon_stock_package_type_category-16.0.1.0.0.7.dist-info/WHEEL
odoo_addon_stock_package_type_category-16.0.1.0.0.7.dist-info/top_level.txt
odoo_addon_stock_package_type_category-16.0.1.0.0.7.dist-info/RECORD
